riyaaaaaaaaaaa/__init__.py
riyaaaaaaaaaaa/love.py
riyaaaaaaaaaaa-1.0.0.dist-info/METADATA
riyaaaaaaaaaaa-1.0.0.dist-info/WHEEL
riyaaaaaaaaaaa-1.0.0.dist-info/top_level.txt
riyaaaaaaaaaaa-1.0.0.dist-info/RECORD
