Metadata-Version: 2.4
Name: riyaaaaaaaaaaa
Version: 1.0.0
Summary: Simple Konkani messages
Project-URL: Homepage, https://github.com/yourusername/riyaaaaaaaaaaa
Classifier: Programming Language :: Python :: 3
Classifier: License :: OSI Approved :: MIT License
Requires-Python: >=3.7
